jspcapy.py
jspcapy-0.4.0.post2.dist-info/LICENSE
jspcapy-0.4.0.post2.dist-info/METADATA
jspcapy-0.4.0.post2.dist-info/WHEEL
jspcapy-0.4.0.post2.dist-info/entry_points.txt
jspcapy-0.4.0.post2.dist-info/top_level.txt
jspcapy-0.4.0.post2.dist-info/zip-safe
jspcapy-0.4.0.post2.dist-info/RECORD
